{
    "widgetName": "Text18",
    "displayName": "Text",
    "iconSVG": "/static/media/icon.97c59b52.svg",
    "topRow": 4,
    "bottomRow": 8,
    "parentRowSpace": 10,
    "type": "TEXT_WIDGET",
    "hideCard": false,
    "animateLoading": true,
    "overflow": "NONE",
    "fontFamily": "{{appsmith.theme.fontFamily.appFont}}",
    "parentColumnSpace": 7.4267578125,
    "dynamicTriggerPathList": [],
    "leftColumn": 15,
    "dynamicBindingPathList": [
        {"key": "fontFamily"},
        {"key": "borderRadius"},
        {"key": "text"}
    ],
    "shouldTruncate": false,
    "truncateButtonColor": "#FFC13D",
    "text": "{{fetchCurrentRelease.data[0].status}}",
    "key": "gtebov7kpk",
    "rightColumn": 63,
    "textAlign": "RIGHT",
    "dynamicHeight": "FIXED",
    "widgetId": "qvbhgr1v8r",
    "isVisible": true,
    "fontStyle": "BOLD",
    "textColor": "#231F20",
    "version": 1,
    "parentId": "on4lna9sof",
    "renderMode": "CANVAS",
    "isLoading": false,
    "borderRadius": "{{appsmith.theme.borderRadius.appBorderRadius}}",
    "maxDynamicHeight": 9000,
    "fontSize": "1rem",
    "minDynamicHeight": 4
}